comfy_catapult/__init__.py
comfy_catapult/api_client.py
comfy_catapult/api_client_base.py
comfy_catapult/catapult.py
comfy_catapult/catapult_base.py
comfy_catapult/catapult_test.py
comfy_catapult/cli.py
comfy_catapult/comfy_schema.py
comfy_catapult/comfy_schema_test.py
comfy_catapult/comfy_utils.py
comfy_catapult/errors.py
comfy_catapult/py.typed
comfy_catapult/remote_file_api_base.py
comfy_catapult/remote_file_api_comfy.py
comfy_catapult/remote_file_api_comfy_test.py
comfy_catapult/remote_file_api_generic.py
comfy_catapult/remote_file_api_local.py
comfy_catapult/url_utils_test.py
comfy_catapult/_internal/__init__.py
comfy_catapult/_internal/url_utils.py
comfy_catapult/_internal/utilities.py
comfy_catapult-3.0.0.dist-info/LICENSE.md
comfy_catapult-3.0.0.dist-info/METADATA
comfy_catapult-3.0.0.dist-info/WHEEL
comfy_catapult-3.0.0.dist-info/top_level.txt
comfy_catapult-3.0.0.dist-info/RECORD
